setup.py
nose_tooslow.egg-info/PKG-INFO
nose_tooslow.egg-info/SOURCES.txt
nose_tooslow.egg-info/dependency_links.txt
nose_tooslow.egg-info/entry_points.txt
nose_tooslow.egg-info/top_level.txt
tooslow/__init__.py
tooslow/tooslow.py