Metadata-Version: 1.1
Name: nose-tooslow
Version: 0.1
Summary: Treat tests that execute too slowly as failed
Home-page: https://github.com/mpirnat/nose-tooslow
Author: Mike Pirnat
Author-email: mpirnat@gmail.com
License: MIT
Platform: UNKNOWN
Classifier: Intended Audience :: Developers
Classifier: Natural Language :: English
Classifier: Operating System :: OS Independent
Classifier: Topic :: Software Development :: Testing
Classifier: Programming Language :: Python :: 2
